tinycircuits_wireling/__init__.py
tinycircuits_wireling/tinycircuits_wireling.py
tinycircuits_wireling-0.0.2.dist-info/LICENSE
tinycircuits_wireling-0.0.2.dist-info/METADATA
tinycircuits_wireling-0.0.2.dist-info/WHEEL
tinycircuits_wireling-0.0.2.dist-info/top_level.txt
tinycircuits_wireling-0.0.2.dist-info/RECORD
